README.rst
httq.py
setup.cfg
setup.py
httq.egg-info/PKG-INFO
httq.egg-info/SOURCES.txt
httq.egg-info/dependency_links.txt
httq.egg-info/entry_points.txt
httq.egg-info/top_level.txt