Metadata-Version: 1.1
Name: httq
Version: 0.0.1
Summary: fast and lightweight HTTP client written in pure Python
Home-page: http://httq.io/
Author: Nigel Small
Author-email: nigel@nigelsmall.com
License: Apache License, Version 2.0
Platform: UNKNOWN
Classifier: Intended Audience :: Developers
Classifier: License :: OSI Approved :: Apache Software License
Classifier: Operating System :: OS Independent
Classifier: Programming Language :: Python :: 2.7
Classifier: Programming Language :: Python :: 3.2
Classifier: Programming Language :: Python :: 3.3
Classifier: Topic :: Internet :: WWW/HTTP
Classifier: Topic :: Software Development
